tuncat/__init__.py
tuncat/bin_trace_video.py
tuncat/nmfunmix1_pertmin_res_MSE_novideo.py
tuncat/nmfunmix_MSE.py
tuncat/run_TUnCaT.py
tuncat/traces_from_masks_mp_mmap_fn_neighbors.py
tuncat/traces_from_masks_mp_shm_neighbors.py
tuncat/traces_from_masks_numba_neighbors.py
tuncat/use_nmfunmix_mp_MSE_novideo.py
tuncat/utils.py
tuncat/more_options/__init__.py
tuncat/more_options/nmfunmix1_pertmin_res_MSE_novideo_2side.py
tuncat/more_options/nmfunmix_MSE_allow0.py
tuncat-1.1.1.dist-info/LICENSE
tuncat-1.1.1.dist-info/METADATA
tuncat-1.1.1.dist-info/WHEEL
tuncat-1.1.1.dist-info/top_level.txt
tuncat-1.1.1.dist-info/RECORD
