Metadata-Version: 2.1
Name: tuncat
Version: 1.1.1
Summary: Temporal Unmixing of Calcium Traces (TUnCaT) is an automatic algorithm to decontaminate false transients from temporal traces generated from fluorescent calcium imaging videos. 
Home-page: https://github.com/YijunBao/TUnCaT
Author: Yijun Bao
Author-email: yijun.bao@duke.edu
Maintainer: Yijun Bao
Maintainer-email: yijun.bao@duke.edu
License: the GNU License, Version 2.0
Project-URL: Source Code, https://github.com/YijunBao/TUnCaT
Project-URL: Citation, https://doi.org/10.5281/zenodo.5764576
Project-URL: Paper, https://doi.org/10.3389/fnins.2021.797421
Platform: all
Classifier: Operating System :: OS Independent
Classifier: Intended Audience :: End Users/Desktop
Classifier: Intended Audience :: Science/Research
Classifier: License :: OSI Approved :: GNU General Public License v2 (GPLv2)
Classifier: Programming Language :: Python :: 3
Classifier: Topic :: Scientific/Engineering :: Bio-Informatics
Requires-Python: >=3
License-File: LICENSE
Requires-Dist: numpy
Requires-Dist: scipy
Requires-Dist: scikit-learn <1.2
Requires-Dist: numba
Requires-Dist: h5py
Requires-Dist: matplotlib
